eqmicro/__init__.py
eqmicro/client/__init__.py
eqmicro/client/http_service.py
eqmicro/client/rpc_disposable.py
eqmicro/client/rpc_receive.py
eqmicro/client/rpc_service.py
eqmicro/components/__init__.py
eqmicro/components/code_msg.py
eqmicro/components/ext_lib.py
eqmicro/components/load_conf_app.py
eqmicro/components/protocol.py
eqmicro/components/protocol_info.py
eqmicro/components/read_conf.py
eqmicro/components/read_module.py
eqmicro/components/scan_services.py
eqmicro/consumer/__init__.py
eqmicro/consumer/service_invalid.py
eqmicro/consumer/service_pull.py
eqmicro/consumer/srvice_call.py
eqmicro/provider/__init__.py
eqmicro/provider/provider_health.py
eqmicro/provider/provider_mgt.py
eqmicro/provider/provider_register.py
eqmicro/register/__init__.py
eqmicro/register/service_change.py
eqmicro/register/service_check.py
eqmicro/register/service_mgt.py
eqmicro/start/__init__.py
eqmicro/start/consumer.py
eqmicro/start/my_http.py
eqmicro/start/provider.py
eqmicro/start/register.py
eqmicro-0.0.2.dist-info/LICENSE
eqmicro-0.0.2.dist-info/METADATA
eqmicro-0.0.2.dist-info/WHEEL
eqmicro-0.0.2.dist-info/top_level.txt
eqmicro-0.0.2.dist-info/RECORD
